{
    "BuildID": "4ce5206a-c380-49e4-a93c-a7a65ce4cb31",
    "Command": "project:build",
    "ProjectID": "35f35fef124d76f4a9621e5a310bcc25",
    "ProjectStateHash": "0e817d7f9884188af64004eebf4a51cdcfb861b52266608c4ecdbc39c87be5a1",
    "StageCompletedAt": 3,
    "EarliestFatalError": 0,
    "StartTime": 1707121805013,
    "EndTime": 1707121865926,
    "PlaygroundUserID": 13720,
    "OperatingSystem": "win32",
    "UnityPackageID": null,
    "TargetPlatform": "develop",
    "UnityVersion": "2021.3.30f1",
    "LunaVersion": "5.5.0",
    "LogCount": 3,
    "Logs": [
        {
            "LogID": "36593f2c-afaa-442f-be93-941f206fe2b9",
            "Order": 2,
            "Timestamp": 1707121866248,
            "Stage": 3,
            "ErrorType": 3,
            "ErrorCode": "LP3007",
            "Description": "You are not using any custom events",
            "Details": [
                "You are not using any custom events. It is recommended to use custom events to have a better understanding of the playable."
            ],
            "DescriptionValues": [
                ""
            ],
            "DetailsValues": [
                ""
            ],
            "LogCount": 1,
            "LinePosition": null,
            "FilePath": "",
            "ClassName": "",
            "MemberName": "",
            "Severity": 0
        },
        {
            "LogID": "5ee1bbee-b464-4762-b987-e94a2115126e",
            "Order": 2,
            "Timestamp": 1707121866250,
            "Stage": 3,
            "ErrorType": 3,
            "ErrorCode": "LP3011",
            "Description": "You are not using any LunaPlaygroundFields attributes.",
            "Details": [
                "You are not using any LunaPlaygroundFields attributes, it allows you to configure your playable to different concepts to find the best variation, which can drastically improve playable performance on all ad networks."
            ],
            "DescriptionValues": null,
            "DetailsValues": null,
            "LogCount": 1,
            "LinePosition": null,
            "FilePath": "",
            "ClassName": "",
            "MemberName": "",
            "Severity": 0
        },
        {
            "LogID": "5abb6470-39b8-44a4-b09e-e4be71a6ade4",
            "Order": 0,
            "Timestamp": 1707121816357,
            "Stage": 1,
            "ErrorType": 2,
            "ErrorCode": "LP1010",
            "Description": "Looks like a collider was scaled, this might affect performance.",
            "Details": [
                "Looks like Tile collider on Tile game object was scaled, this might affect performance."
            ],
            "DescriptionValues": [],
            "DetailsValues": [
                "Tile",
                "Tile"
            ],
            "LogCount": 1,
            "LinePosition": 0,
            "FilePath": "",
            "ClassName": "",
            "MemberName": "",
            "Severity": 0
        }
    ]
}